{"attr":[{"isAnimated":false,"attributes":{"r":"193.65949499056327","cx":"550","cy":"344.0625","fill":"rgba(233, 233, 234, 1)","stroke":"rgba(158, 198, 242, 1)","stroke-width":"9","data-tool":"true","type-tool":"circle","id":"circle-1716320694562-jfbtqxqn7"},"origin":{"x":522.0000152587891,"y":328.0625}},{"isAnimated":true,"attributes":{"x1":"488","y1":"120.0625","x2":"609","y2":"119.0625","data-tool":"true","type-tool":"line","stroke-linecap":"round","fill":"rgba(233, 233, 234, 1)","stroke":"rgba(158, 198, 242, 1)","stroke-width":"9","linecap":"round","linejoin":"round","id":"line-1716320715107-hyviv0shs"},"origin":{"x":548.5,"y":120.5625}},{"isAnimated":false,"attributes":{"x1":"554","y1":"516.0625","x2":"553","y2":"459.0625","data-tool":"true","type-tool":"line","stroke-linecap":"round","fill":"rgba(233, 233, 234, 1)","stroke":"rgba(158, 198, 242, 1)","stroke-width":"9","linecap":"round","linejoin":"round","id":"line-1716320865677-550oywvaq"},"origin":{"x":553.5,"y":487.5625}},{"isAnimated":false,"attributes":{"x1":"729","y1":"343.0625","x2":"657","y2":"343.0625","data-tool":"true","type-tool":"line","stroke-linecap":"round","fill":"rgba(233, 233, 234, 1)","stroke":"rgba(158, 198, 242, 1)","stroke-width":"9","linecap":"round","linejoin":"round","id":"line-1716320937572-eclnpmdpa"},"origin":{"x":693,"y":343.0625}},{"isAnimated":false,"attributes":{"x1":"373","y1":"345.0625","x2":"444","y2":"345.0625","data-tool":"true","type-tool":"line","stroke-linecap":"round","fill":"rgba(233, 233, 234, 1)","stroke":"rgba(158, 198, 242, 1)","stroke-width":"9","linecap":"round","linejoin":"round","id":"line-1716320942727-u49j9te6n"},"origin":{"x":401.5,"y":340.0625}},{"isAnimated":false,"attributes":{"x1":"549","y1":"177.0625","x2":"550","y2":"250.0625","data-tool":"true","type-tool":"line","stroke-linecap":"round","fill":"rgba(233, 233, 234, 1)","stroke":"rgba(158, 198, 242, 1)","stroke-width":"9","linecap":"round","linejoin":"round","id":"line-1716320991937-vp4a2hvgk"},"origin":{"x":549.5,"y":213.5625}},{"isAnimated":false,"attributes":{"x1":"415","y1":"458.0625","x2":"441","y2":"439.0625","data-tool":"true","type-tool":"line","stroke-linecap":"round","fill":"rgba(233, 233, 234, 1)","stroke":"rgba(158, 198, 242, 1)","stroke-width":"9","linecap":"round","linejoin":"round","id":"line-1716321025682-9dnd1k0w2"},"origin":{"x":428,"y":448.5625}},{"isAnimated":false,"attributes":{"x1":"659","y1":"433.0625","x2":"686","y2":"452.0625","data-tool":"true","type-tool":"line","stroke-linecap":"round","fill":"rgba(233, 233, 234, 1)","stroke":"rgba(158, 198, 242, 1)","stroke-width":"9","linecap":"round","linejoin":"round","id":"line-1716321045448-db2ws36kq"},"origin":{"x":672.5,"y":442.5625}},{"isAnimated":false,"attributes":{"x1":"418","y1":"222.0625","x2":"441","y2":"243.0625","data-tool":"true","type-tool":"line","stroke-linecap":"round","fill":"rgba(233, 233, 234, 1)","stroke":"rgba(158, 198, 242, 1)","stroke-width":"9","linecap":"round","linejoin":"round","id":"line-1716321050044-jep00qnmv"},"origin":{"x":429.5,"y":232.5625}},{"isAnimated":false,"attributes":{"x1":"687","y1":"230.0625","x2":"662","y2":"254.0625","data-tool":"true","type-tool":"line","stroke-linecap":"round","fill":"rgba(233, 233, 234, 1)","stroke":"rgba(158, 198, 242, 1)","stroke-width":"9","linecap":"round","linejoin":"round","id":"line-1716321056178-vgsdfqzss"},"origin":{"x":674.5,"y":242.0625}},{"isAnimated":true,"attributes":{"x1":"549","y1":"216.0625","x2":"551","y2":"342.0625","data-tool":"true","type-tool":"line","stroke-linecap":"round","fill":"rgba(126, 181, 245, 1)","stroke":"rgba(126, 181, 245, 1)","stroke-width":"9","linecap":"round","linejoin":"round","id":"line-1716321227184-znvv2hzmi"},"origin":{"x":551,"y":342.0625}},{"isAnimated":false,"attributes":{"r":"5.830951894845301","cx":"551","cy":"338.0625","fill":"rgba(126, 181, 245, 1)","stroke":"rgba(126, 181, 245, 1)","stroke-width":"9","data-tool":"true","type-tool":"circle","id":"circle-1716321243256-4ufsbwvjp"},"origin":{"x":550.0000190734863,"y":341.0624885559082}}],"duration":2}